MANIFEST.in
README.md
README.rst
setup.py
joe/__init__.py
joe/joe.py
joe.egg-info/PKG-INFO
joe.egg-info/SOURCES.txt
joe.egg-info/dependency_links.txt
joe.egg-info/entry_points.txt
joe.egg-info/pbr.json
joe.egg-info/requires.txt
joe.egg-info/top_level.txt
joe/data/.git
joe/data/Actionscript.gitignore
joe/data/Ada.gitignore
joe/data/Agda.gitignore
joe/data/Android.gitignore
joe/data/AppceleratorTitanium.gitignore
joe/data/ArchLinuxPackages.gitignore
joe/data/Autotools.gitignore
joe/data/C++.gitignore
joe/data/C.gitignore
joe/data/CFWheels.gitignore
joe/data/CMake.gitignore
joe/data/CONTRIBUTING.md
joe/data/CakePHP.gitignore
joe/data/ChefCookbook.gitignore
joe/data/Clojure.gitignore
joe/data/CodeIgniter.gitignore
joe/data/CommonLisp.gitignore
joe/data/Composer.gitignore
joe/data/Concrete5.gitignore
joe/data/Coq.gitignore
joe/data/CraftCMS.gitignore
joe/data/DM.gitignore
joe/data/Dart.gitignore
joe/data/Delphi.gitignore
joe/data/Drupal.gitignore
joe/data/EPiServer.gitignore
joe/data/Eagle.gitignore
joe/data/Elisp.gitignore
joe/data/Elixir.gitignore
joe/data/Erlang.gitignore
joe/data/ExpressionEngine.gitignore
joe/data/ExtJs.gitignore
joe/data/Fancy.gitignore
joe/data/Finale.gitignore
joe/data/ForceDotCom.gitignore
joe/data/Fortran.gitignore
joe/data/FuelPHP.gitignore
joe/data/GWT.gitignore
joe/data/Gcov.gitignore
joe/data/GitBook.gitignore
joe/data/Global
joe/data/Go.gitignore
joe/data/Gradle.gitignore
joe/data/Grails.gitignore
joe/data/Haskell.gitignore
joe/data/IGORPro.gitignore
joe/data/Idris.gitignore
joe/data/Java.gitignore
joe/data/Jboss.gitignore
joe/data/Jekyll.gitignore
joe/data/Joomla.gitignore
joe/data/Jython.gitignore
joe/data/Kohana.gitignore
joe/data/LICENSE
joe/data/LabVIEW.gitignore
joe/data/Laravel.gitignore
joe/data/Leiningen.gitignore
joe/data/LemonStand.gitignore
joe/data/Lilypond.gitignore
joe/data/Lithium.gitignore
joe/data/Lua.gitignore
joe/data/Magento.gitignore
joe/data/Maven.gitignore
joe/data/Mercury.gitignore
joe/data/MetaProgrammingSystem.gitignore
joe/data/Meteor.gitignore
joe/data/Nanoc.gitignore
joe/data/Nim.gitignore
joe/data/Node.gitignore
joe/data/OCaml.gitignore
joe/data/Objective-C.gitignore
joe/data/Opa.gitignore
