Metadata-Version: 1.0
Name: joe
Version: 0.0.7
Summary: joe generates .gitignore files from the command line for you.
Home-page: http://github.com/karan/joe
Author: Karan Goel
Author-email: karan@goel.io
License: MIT
Keywords: gitignore,git,github,command line,cli
Platform: UNKNOWN
